Workbook

Sheet Sheet1
A1: PR. 1 Fundamental Booster | C1: Student ID | D1: Name | E1: Math | F1: Science | G1: English | H1: Enrollment Date | I1: Grade (Math) | J1: Sales ID | K1: Product | L1: Region | M1: Salesperson | N1: Amount | O1: Date | P1: Discount Eligible? | Q1: Employee ID | R1: Name | S1: Department | T1: Salary | U1: Joining Date | V1: Years of Service
A2: Topics: - Relative & Absolute References, Formatting, Data Input - IF Formulas, Nested IFs, IF with AND/OR - COUNTIFS, SUMIFS, AVERAGEIFS - Lookup Functions (VLOOKUP, XLOOKUP, XMATCH) - INDEX/MATCH for dynamic searches - TEXT Functions for string manipulations - INDIRECT and OFFSET for dynamic references - Date/Time, Math Functions, FILTER function Main Tasks: 1. Apply IF formulas to classify student grades. 2. Use COUNTIFS to count students scoring above 60. 3. Use VLOOKUP to find a product price from sales data. 4. Apply XLOOKUP to fetch employee salaries dynamically. 5. Format and analyze date of joining in Employee data. 6. Use FILTER function to extract students with grades above 80. Deliverable: Complete the given worksheets by applying the required formulas in respective sheets. | C2: 1001 | D2: Student 1 | E2: 61 | F2: 48 | G2: 76 | H2: 43101 | I2: =IF(E2>=90,"A",IF(E2>=75,"B",IF(E2>=60,"C","F"))) -> C | J2: 2001 | K2: Keyboard | L2: South | M2: Person 1 | N2: 7048 | O2: 44927 | P2: =IF(OR(N2>40000,K2="Laptop"),"Yes","No") -> No | Q2: 3001 | R2: Employee 1 | S2: Finance | T2: 86766 | U2: 42005 | V2: =IF(U2>TODAY(),0,DATEDIF(U2,TODAY(),"Y")) -> 11
C3: 1002 | D3: Student 2 | E3: 78 | F3: 76 | G3: 70 | H3: 43281 | I3: =IF(E3>=90,"A",IF(E3>=75,"B",IF(E3>=60,"C","F"))) -> B | J3: 2002 | K3: Printer | L3: West | M3: Person 2 | N3: 17428 | O3: 44942 | P3: =IF(OR(N3>40000,K3="Laptop"),"Yes","No") -> No | Q3: 3002 | R3: Employee 2 | S3: Finance | T3: 31943 | U3: 42255 | V3: =IF(U3>TODAY(),0,DATEDIF(U3,TODAY(),"Y")) -> 10
C4: 1003 | D4: Student 3 | E4: 97 | F4: 60 | G4: 51 | H4: 43461 | I4: =IF(E4>=90,"A",IF(E4>=75,"B",IF(E4>=60,"C","F"))) -> A | J4: 2003 | K4: Mouse | L4: South | M4: Person 3 | N4: 23672 | O4: 44957 | P4: =IF(OR(N4>40000,K4="Laptop"),"Yes","No") -> No | Q4: 3003 | R4: Employee 3 | S4: HR | T4: 63374 | U4: 42505 | V4: =IF(U4>TODAY(),0,DATEDIF(U4,TODAY(),"Y")) -> 9
A5: Essential Tasks | C5: 1004 | D5: Student 4 | E5: 74 | F5: 55 | G5: 46 | H5: 43641 | I5: =IF(E5>=90,"A",IF(E5>=75,"B",IF(E5>=60,"C","F"))) -> C | J5: 2004 | K5: Printer | L5: East | M5: Person 4 | N5: 5264 | O5: 44972 | P5: =IF(OR(N5>40000,K5="Laptop"),"Yes","No") -> No | Q5: 3004 | R5: Employee 4 | S5: Finance | T5: 109972 | U5: 42755 | V5: =IF(U5>TODAY(),0,DATEDIF(U5,TODAY(),"Y")) -> 9
A6: Relative & Absolute Cell References, Formatting, and Data Input | C6: 1005 | D6: Student 5 | E6: 68 | F6: 74 | G6: 84 | H6: 43821 | I6: =IF(E6>=90,"A",IF(E6>=75,"B",IF(E6>=60,"C","F"))) -> C | J6: 2005 | K6: Keyboard | L6: North | M6: Person 5 | N6: 43388 | O6: 44987 | P6: =IF(OR(N6>40000,K6="Laptop"),"Yes","No") -> Yes | Q6: 3005 | R6: Employee 5 | S6: IT | T6: 54149 | U6: 43005 | V6: =IF(U6>TODAY(),0,DATEDIF(U6,TODAY(),"Y")) -> 8
A7: Enter and format data (bold, italic, currency, date, custom formats). | C7: 1006 | D7: Student 6 | E7: 80 | F7: 70 | G7: 65 | H7: 44001 | I7: =IF(E7>=90,"A",IF(E7>=75,"B",IF(E7>=60,"C","F"))) -> B | J7: 2006 | K7: Mouse | L7: North | M7: Person 6 | N7: 19757 | O7: 45002 | P7: =IF(OR(N7>40000,K7="Laptop"),"Yes","No") -> No | Q7: 3006 | R7: Employee 6 | S7: IT | T7: 78689 | U7: 43255 | V7: =IF(U7>TODAY(),0,DATEDIF(U7,TODAY(),"Y")) -> 7
A8: Use absolute ($A$1) and relative (A1) references in formulas. | C8: 1007 | D8: Student 7 | E8: 75 | F8: 47 | G8: 78 | H8: 44181 | I8: =IF(E8>=90,"A",IF(E8>=75,"B",IF(E8>=60,"C","F"))) -> B | J8: 2007 | K8: Mouse | L8: East | M8: Person 7 | N8: 32058 | O8: 45017 | P8: =IF(OR(N8>40000,K8="Laptop"),"Yes","No") -> No | Q8: 3007 | R8: Employee 7 | S8: Marketing | T8: 35960 | U8: 43505 | V8: =IF(U8>TODAY(),0,DATEDIF(U8,TODAY(),"Y")) -> 7
C9: 1008 | D9: Student 8 | E9: 94 | F9: 67 | G9: 64 | H9: 44361 | I9: =IF(E9>=90,"A",IF(E9>=75,"B",IF(E9>=60,"C","F"))) -> A | J9: 2008 | K9: Keyboard | L9: East | M9: Person 8 | N9: 46429 | O9: 45032 | P9: =IF(OR(N9>40000,K9="Laptop"),"Yes","No") -> Yes | Q9: 3008 | R9: Employee 8 | S9: IT | T9: 91659 | U9: 43755 | V9: =IF(U9>TODAY(),0,DATEDIF(U9,TODAY(),"Y")) -> 6
A10: Using IF Formula & Nesting IF Formulas | C10: 1009 | D10: Student 9 | E10: 41 | F10: 75 | G10: 56 | H10: 44541 | I10: =IF(E10>=90,"A",IF(E10>=75,"B",IF(E10>=60,"C","F"))) -> F | J10: 2009 | K10: Printer | L10: East | M10: Person 9 | N10: 19746 | O10: 45047 | P10: =IF(OR(N10>40000,K10="Laptop"),"Yes","No") -> No | Q10: 3009 | R10: Employee 9 | S10: IT | T10: 90423 | U10: 44005 | V10: =IF(U10>TODAY(),0,DATEDIF(U10,TODAY(),"Y")) -> 5
A11: Classify students' grades based on their scores. | C11: 1010 | D11: Student 10 | E11: 98 | F11: 54 | G11: 58 | H11: 44721 | I11: =IF(E11>=90,"A",IF(E11>=75,"B",IF(E11>=60,"C","F"))) -> A | J11: 2010 | K11: Keyboard | L11: South | M11: Person 10 | N11: 35185 | O11: 45062 | P11: =IF(OR(N11>40000,K11="Laptop"),"Yes","No") -> No | Q11: 3010 | R11: Employee 10 | S11: HR | T11: 107877 | U11: 44255 | V11: =IF(U11>TODAY(),0,DATEDIF(U11,TODAY(),"Y")) -> 5
A12: Compute discounts for sales based on price thresholds. | C12: 1011 | D12: Student 11 | E12: 73 | F12: 79 | G12: 53 | H12: 44901 | I12: =IF(E12>=90,"A",IF(E12>=75,"B",IF(E12>=60,"C","F"))) -> C | J12: 2011 | K12: Keyboard | L12: East | M12: Person 11 | N12: 33920 | O12: 45077 | P12: =IF(OR(N12>40000,K12="Laptop"),"Yes","No") -> No | Q12: 3011 | R12: Employee 11 | S12: Finance | T12: 107634 | U12: 44505 | V12: =IF(U12>TODAY(),0,DATEDIF(U12,TODAY(),"Y")) -> 4
C13: 1012 | D13: Student 12 | E13: 85 | F13: 89 | G13: 79 | H13: 45081 | I13: =IF(E13>=90,"A",IF(E13>=75,"B",IF(E13>=60,"C","F"))) -> B | J13: 2012 | K13: Monitor | L13: North | M13: Person 12 | N13: 35611 | O13: 45092 | P13: =IF(OR(N13>40000,K13="Laptop"),"Yes","No") -> No | Q13: 3012 | R13: Employee 12 | S13: Finance | T13: 35226 | U13: 44755 | V13: =IF(U13>TODAY(),0,DATEDIF(U13,TODAY(),"Y")) -> 3
A14: Using IF with AND/OR Formulas | C14: 1013 | D14: Student 13 | E14: 98 | F14: 90 | G14: 97 | H14: 45261 | I14: =IF(E14>=90,"A",IF(E14>=75,"B",IF(E14>=60,"C","F"))) -> A | J14: 2013 | K14: Laptop | L14: East | M14: Person 13 | N14: 15560 | O14: 45107 | P14: =IF(OR(N14>40000,K14="Laptop"),"Yes","No") -> Yes | Q14: 3013 | R14: Employee 13 | S14: HR | T14: 40872 | U14: 45005 | V14: =IF(U14>TODAY(),0,DATEDIF(U14,TODAY(),"Y")) -> 3
A15: Identify students who scored above 80 in both Math & Science using IF(AND(...)). | C15: 1014 | D15: Student 14 | E15: 93 | F15: 40 | G15: 44 | H15: 45441 | I15: =IF(E15>=90,"A",IF(E15>=75,"B",IF(E15>=60,"C","F"))) -> A | J15: 2014 | K15: Laptop | L15: South | M15: Person 14 | N15: 7283 | O15: 45122 | P15: =IF(OR(N15>40000,K15="Laptop"),"Yes","No") -> Yes | Q15: 3014 | R15: Employee 14 | S15: HR | T15: 55378 | U15: 45255 | V15: =IF(U15>TODAY(),0,DATEDIF(U15,TODAY(),"Y")) -> 2
A16: Determine whether a product is eligible for discount using IF(OR(...)). | C16: 1015 | D16: Student 15 | E16: 70 | F16: 51 | G16: 75 | H16: 45621 | I16: =IF(E16>=90,"A",IF(E16>=75,"B",IF(E16>=60,"C","F"))) -> C | J16: 2015 | K16: Laptop | L16: East | M16: Person 15 | N16: 15678 | O16: 45137 | P16: =IF(OR(N16>40000,K16="Laptop"),"Yes","No") -> Yes | Q16: 3015 | R16: Employee 15 | S16: HR | T16: 63297 | U16: 45505 | V16: =IF(U16>TODAY(),0,DATEDIF(U16,TODAY(),"Y")) -> 1
C17: 1016 | D17: Student 16 | E17: 98 | F17: 77 | G17: 60 | H17: 45801 | I17: =IF(E17>=90,"A",IF(E17>=75,"B",IF(E17>=60,"C","F"))) -> A | J17: 2016 | K17: Mouse | L17: East | M17: Person 16 | N17: 5277 | O17: 45152 | P17: =IF(OR(N17>40000,K17="Laptop"),"Yes","No") -> No | Q17: 3016 | R17: Employee 16 | S17: Finance | T17: 114173 | U17: 45755 | V17: =IF(U17>TODAY(),0,DATEDIF(U17,TODAY(),"Y")) -> 0
A18: COUNTIFS, SUMIFS, AVERAGEIFS | C18: 1017 | D18: Student 17 | E18: 66 | F18: 59 | G18: 40 | H18: 45981 | I18: =IF(E18>=90,"A",IF(E18>=75,"B",IF(E18>=60,"C","F"))) -> C | J18: 2017 | K18: Monitor | L18: North | M18: Person 17 | N18: 41871 | O18: 45167 | P18: =IF(OR(N18>40000,K18="Laptop"),"Yes","No") -> Yes | Q18: 3017 | R18: Employee 17 | S18: HR | T18: 86915 | U18: 46005 | V18: =IF(U18>TODAY(),0,DATEDIF(U18,TODAY(),"Y")) -> 0
A19: Count the number of students who scored above 50 in Math. | C19: 1018 | D19: Student 18 | E19: 82 | F19: 48 | G19: 79 | H19: 46161 | I19: =IF(E19>=90,"A",IF(E19>=75,"B",IF(E19>=60,"C","F"))) -> B | J19: 2018 | K19: Monitor | L19: West | M19: Person 18 | N19: 38161 | O19: 45182 | P19: =IF(OR(N19>40000,K19="Laptop"),"Yes","No") -> No | Q19: 3018 | R19: Employee 18 | S19: IT | T19: 116284 | U19: 46255 | V19: =IF(U19>TODAY(),0,DATEDIF(U19,TODAY(),"Y")) -> 0
A20: Sum total sales for a specific region and product. | C20: 1019 | D20: Student 19 | E20: 90 | F20: 78 | G20: 60 | H20: 46341 | I20: =IF(E20>=90,"A",IF(E20>=75,"B",IF(E20>=60,"C","F"))) -> A | J20: 2019 | K20: Mouse | L20: West | M20: Person 19 | N20: 30436 | O20: 45197 | P20: =IF(OR(N20>40000,K20="Laptop"),"Yes","No") -> No | Q20: 3019 | R20: Employee 19 | S20: Marketing | T20: 116283 | U20: 46505 | V20: =IF(U20>TODAY(),0,DATEDIF(U20,TODAY(),"Y")) -> 0
A21: Calculate the average score for students who scored above 60. | C21: 1020 | D21: Student 20 | E21: 83 | F21: 92 | G21: 55 | H21: 46521 | I21: =IF(E21>=90,"A",IF(E21>=75,"B",IF(E21>=60,"C","F"))) -> B | J21: 2020 | K21: Printer | L21: West | M21: Person 20 | N21: 33953 | O21: 45212 | P21: =IF(OR(N21>40000,K21="Laptop"),"Yes","No") -> No | Q21: 3020 | R21: Employee 20 | S21: Marketing | T21: 99924 | U21: 46755 | V21: =IF(U21>TODAY(),0,DATEDIF(U21,TODAY(),"Y")) -> 0
A23: VLOOKUP Function
A24: Fetch student names based on ID from a separate dataset.
A25: Retrieve product prices based on product codes.
A27: INDEX and MATCH Functions
A28: Find sales values for a specific salesperson in a specific month.
A29: Look up employee details dynamically without column restrictions.
A31: Excel TEXT Functions
A32: Extract the first name from full names using LEFT and FIND.
A33: Convert names to uppercase/lowercase using UPPER(), LOWER().
A35: XLOOKUP Function
A36: Search for salesperson performance based on flexible search criteria.
A37: Find employee salaries without worrying about sorted data.
... A58: Quick Summary (COUNTIFS / SUMIFS / AVERAGEIFS)
A59: Students scoring > 50 in Math (COUNTIFS) | B59: =COUNTIFS(E2:E21,">50") -> 19
A60: Avg Math score where Math > 60 (AVERAGEIFS) | B60: =AVERAGEIFS(E2:E21,E2:E21,">60") -> 82.263158
A61: Total East Keyboard sales (SUMIFS) | B61: =SUMIFS(N2:N21,L2:L21,"East",K2:K21,"Keyboard") -> 80349
A62: Count Laptop East sales (COUNTIFS) | B62: =COUNTIFS(K2:K21,"Laptop",L2:L21,"East") -> 2
A63: Avg IT Dept salary (AVERAGEIFS) | B63: =AVERAGEIFS(T2:T21,S2:S21,"IT") -> 86240.8

Sheet Sheet2

Sheet Main Tasks
A1: PR.1 Fundamental Booster — Main Tasks Deliverable
A2: All 6 required tasks solved with Excel formulas referencing the source data in Sheet1
A4: TASK 1 — Apply IF Formulas to Classify Student Grades (≥90→A | ≥75→B | ≥60→C | else→F)
A5: Student ID | B5: Name | C5: Math | D5: Science | E5: English | F5: Math Grade | G5: Science Grade | H5: English Grade | I5: Overall Grade | J5: Discount on Sales (IF)
A6: =Sheet1!C2 -> 1001 | B6: =Sheet1!D2 -> Student 1 | C6: =Sheet1!E2 -> 61 | D6: =Sheet1!F2 -> 48 | E6: =Sheet1!G2 -> 76 | F6: =IF(Sheet1!E2>=90,"A",IF(Sheet1!E2>=75,"B",IF(Sheet1!E2>=60,"C","F"))) -> C | G6: =IF(Sheet1!F2>=90,"A",IF(Sheet1!F2>=75,"B",IF(Sheet1!F2>=60,"C","F"))) -> F | H6: =IF(Sheet1!G2>=90,"A",IF(Sheet1!G2>=75,"B",IF(Sheet1!G2>=60,"C","F"))) -> B | I6: =IF(AVERAGE(Sheet1!E2:G2)>=90,"A",IF(AVERAGE(Sheet1!E2:G2)>=75,"B",IF(AVERAGE(Sheet1!E2:G2)>=60,"C","F"))) -> C | J6: =IF(Sheet1!N2>30000,"10% Discount","No Discount") -> No Discount
A7: =Sheet1!C3 -> 1002 | B7: =Sheet1!D3 -> Student 2 | C7: =Sheet1!E3 -> 78 | D7: =Sheet1!F3 -> 76 | E7: =Sheet1!G3 -> 70 | F7: =IF(Sheet1!E3>=90,"A",IF(Sheet1!E3>=75,"B",IF(Sheet1!E3>=60,"C","F"))) -> B | G7: =IF(Sheet1!F3>=90,"A",IF(Sheet1!F3>=75,"B",IF(Sheet1!F3>=60,"C","F"))) -> B | H7: =IF(Sheet1!G3>=90,"A",IF(Sheet1!G3>=75,"B",IF(Sheet1!G3>=60,"C","F"))) -> C | I7: =IF(AVERAGE(Sheet1!E3:G3)>=90,"A",IF(AVERAGE(Sheet1!E3:G3)>=75,"B",IF(AVERAGE(Sheet1!E3:G3)>=60,"C","F"))) -> C | J7: =IF(Sheet1!N3>30000,"10% Discount","No Discount") -> No Discount
A8: =Sheet1!C4 -> 1003 | B8: =Sheet1!D4 -> Student 3 | C8: =Sheet1!E4 -> 97 | D8: =Sheet1!F4 -> 60 | E8: =Sheet1!G4 -> 51 | F8: =IF(Sheet1!E4>=90,"A",IF(Sheet1!E4>=75,"B",IF(Sheet1!E4>=60,"C","F"))) -> A | G8: =IF(Sheet1!F4>=90,"A",IF(Sheet1!F4>=75,"B",IF(Sheet1!F4>=60,"C","F"))) -> C | H8: =IF(Sheet1!G4>=90,"A",IF(Sheet1!G4>=75,"B",IF(Sheet1!G4>=60,"C","F"))) -> F | I8: =IF(AVERAGE(Sheet1!E4:G4)>=90,"A",IF(AVERAGE(Sheet1!E4:G4)>=75,"B",IF(AVERAGE(Sheet1!E4:G4)>=60,"C","F"))) -> C | J8: =IF(Sheet1!N4>30000,"10% Discount","No Discount") -> No Discount
A9: =Sheet1!C5 -> 1004 | B9: =Sheet1!D5 -> Student 4 | C9: =Sheet1!E5 -> 74 | D9: =Sheet1!F5 -> 55 | E9: =Sheet1!G5 -> 46 | F9: =IF(Sheet1!E5>=90,"A",IF(Sheet1!E5>=75,"B",IF(Sheet1!E5>=60,"C","F"))) -> C | G9: =IF(Sheet1!F5>=90,"A",IF(Sheet1!F5>=75,"B",IF(Sheet1!F5>=60,"C","F"))) -> F | H9: =IF(Sheet1!G5>=90,"A",IF(Sheet1!G5>=75,"B",IF(Sheet1!G5>=60,"C","F"))) -> F | I9: =IF(AVERAGE(Sheet1!E5:G5)>=90,"A",IF(AVERAGE(Sheet1!E5:G5)>=75,"B",IF(AVERAGE(Sheet1!E5:G5)>=60,"C","F"))) -> F | J9: =IF(Sheet1!N5>30000,"10% Discount","No Discount") -> No Discount
A10: =Sheet1!C6 -> 1005 | B10: =Sheet1!D6 -> Student 5 | C10: =Sheet1!E6 -> 68 | D10: =Sheet1!F6 -> 74 | E10: =Sheet1!G6 -> 84 | F10: =IF(Sheet1!E6>=90,"A",IF(Sheet1!E6>=75,"B",IF(Sheet1!E6>=60,"C","F"))) -> C | G10: =IF(Sheet1!F6>=90,"A",IF(Sheet1!F6>=75,"B",IF(Sheet1!F6>=60,"C","F"))) -> C | H10: =IF(Sheet1!G6>=90,"A",IF(Sheet1!G6>=75,"B",IF(Sheet1!G6>=60,"C","F"))) -> B | I10: =IF(AVERAGE(Sheet1!E6:G6)>=90,"A",IF(AVERAGE(Sheet1!E6:G6)>=75,"B",IF(AVERAGE(Sheet1!E6:G6)>=60,"C","F"))) -> B | J10: =IF(Sheet1!N6>30000,"10% Discount","No Discount") -> 10% Discount
A11: =Sheet1!C7 -> 1006 | B11: =Sheet1!D7 -> Student 6 | C11: =Sheet1!E7 -> 80 | D11: =Sheet1!F7 -> 70 | E11: =Sheet1!G7 -> 65 | F11: =IF(Sheet1!E7>=90,"A",IF(Sheet1!E7>=75,"B",IF(Sheet1!E7>=60,"C","F"))) -> B | G11: =IF(Sheet1!F7>=90,"A",IF(Sheet1!F7>=75,"B",IF(Sheet1!F7>=60,"C","F"))) -> C | H11: =IF(Sheet1!G7>=90,"A",IF(Sheet1!G7>=75,"B",IF(Sheet1!G7>=60,"C","F"))) -> C | I11: =IF(AVERAGE(Sheet1!E7:G7)>=90,"A",IF(AVERAGE(Sheet1!E7:G7)>=75,"B",IF(AVERAGE(Sheet1!E7:G7)>=60,"C","F"))) -> C | J11: =IF(Sheet1!N7>30000,"10% Discount","No Discount") -> No Discount
A12: =Sheet1!C8 -> 1007 | B12: =Sheet1!D8 -> Student 7 | C12: =Sheet1!E8 -> 75 | D12: =Sheet1!F8 -> 47 | E12: =Sheet1!G8 -> 78 | F12: =IF(Sheet1!E8>=90,"A",IF(Sheet1!E8>=75,"B",IF(Sheet1!E8>=60,"C","F"))) -> B | G12: =IF(Sheet1!F8>=90,"A",IF(Sheet1!F8>=75,"B",IF(Sheet1!F8>=60,"C","F"))) -> F | H12: =IF(Sheet1!G8>=90,"A",IF(Sheet1!G8>=75,"B",IF(Sheet1!G8>=60,"C","F"))) -> B | I12: =IF(AVERAGE(Sheet1!E8:G8)>=90,"A",IF(AVERAGE(Sheet1!E8:G8)>=75,"B",IF(AVERAGE(Sheet1!E8:G8)>=60,"C","F"))) -> C | J12: =IF(Sheet1!N8>30000,"10% Discount","No Discount") -> 10% Discount
A13: =Sheet1!C9 -> 1008 | B13: =Sheet1!D9 -> Student 8 | C13: =Sheet1!E9 -> 94 | D13: =Sheet1!F9 -> 67 | E13: =Sheet1!G9 -> 64 | F13: =IF(Sheet1!E9>=90,"A",IF(Sheet1!E9>=75,"B",IF(Sheet1!E9>=60,"C","F"))) -> A | G13: =IF(Sheet1!F9>=90,"A",IF(Sheet1!F9>=75,"B",IF(Sheet1!F9>=60,"C","F"))) -> C | H13: =IF(Sheet1!G9>=90,"A",IF(Sheet1!G9>=75,"B",IF(Sheet1!G9>=60,"C","F"))) -> C | I13: =IF(AVERAGE(Sheet1!E9:G9)>=90,"A",IF(AVERAGE(Sheet1!E9:G9)>=75,"B",IF(AVERAGE(Sheet1!E9:G9)>=60,"C","F"))) -> B | J13: =IF(Sheet1!N9>30000,"10% Discount","No Discount") -> 10% Discount
A14: =Sheet1!C10 -> 1009 | B14: =Sheet1!D10 -> Student 9 | C14: =Sheet1!E10 -> 41 | D14: =Sheet1!F10 -> 75 | E14: =Sheet1!G10 -> 56 | F14: =IF(Sheet1!E10>=90,"A",IF(Sheet1!E10>=75,"B",IF(Sheet1!E10>=60,"C","F"))) -> F | G14: =IF(Sheet1!F10>=90,"A",IF(Sheet1!F10>=75,"B",IF(Sheet1!F10>=60,"C","F"))) -> B | H14: =IF(Sheet1!G10>=90,"A",IF(Sheet1!G10>=75,"B",IF(Sheet1!G10>=60,"C","F"))) -> F | I14: =IF(AVERAGE(Sheet1!E10:G10)>=90,"A",IF(AVERAGE(Sheet1!E10:G10)>=75,"B",IF(AVERAGE(Sheet1!E10:G10)>=60,"C","F"))) -> F | J14: =IF(Sheet1!N10>30000,"10% Discount","No Discount") -> No Discount
A15: =Sheet1!C11 -> 1010 | B15: =Sheet1!D11 -> Student 10 | C15: =Sheet1!E11 -> 98 | D15: =Sheet1!F11 -> 54 | E15: =Sheet1!G11 -> 58 | F15: =IF(Sheet1!E11>=90,"A",IF(Sheet1!E11>=75,"B",IF(Sheet1!E11>=60,"C","F"))) -> A | G15: =IF(Sheet1!F11>=90,"A",IF(Sheet1!F11>=75,"B",IF(Sheet1!F11>=60,"C","F"))) -> F | H15: =IF(Sheet1!G11>=90,"A",IF(Sheet1!G11>=75,"B",IF(Sheet1!G11>=60,"C","F"))) -> F | I15: =IF(AVERAGE(Sheet1!E11:G11)>=90,"A",IF(AVERAGE(Sheet1!E11:G11)>=75,"B",IF(AVERAGE(Sheet1!E11:G11)>=60,"C","F"))) -> C | J15: =IF(Sheet1!N11>30000,"10% Discount","No Discount") -> 10% Discount
A16: =Sheet1!C12 -> 1011 | B16: =Sheet1!D12 -> Student 11 | C16: =Sheet1!E12 -> 73 | D16: =Sheet1!F12 -> 79 | E16: =Sheet1!G12 -> 53 | F16: =IF(Sheet1!E12>=90,"A",IF(Sheet1!E12>=75,"B",IF(Sheet1!E12>=60,"C","F"))) -> C | G16: =IF(Sheet1!F12>=90,"A",IF(Sheet1!F12>=75,"B",IF(Sheet1!F12>=60,"C","F"))) -> B | H16: =IF(Sheet1!G12>=90,"A",IF(Sheet1!G12>=75,"B",IF(Sheet1!G12>=60,"C","F"))) -> F | I16: =IF(AVERAGE(Sheet1!E12:G12)>=90,"A",IF(AVERAGE(Sheet1!E12:G12)>=75,"B",IF(AVERAGE(Sheet1!E12:G12)>=60,"C","F"))) -> C | J16: =IF(Sheet1!N12>30000,"10% Discount","No Discount") -> 10% Discount
A17: =Sheet1!C13 -> 1012 | B17: =Sheet1!D13 -> Student 12 | C17: =Sheet1!E13 -> 85 | D17: =Sheet1!F13 -> 89 | E17: =Sheet1!G13 -> 79 | F17: =IF(Sheet1!E13>=90,"A",IF(Sheet1!E13>=75,"B",IF(Sheet1!E13>=60,"C","F"))) -> B | G17: =IF(Sheet1!F13>=90,"A",IF(Sheet1!F13>=75,"B",IF(Sheet1!F13>=60,"C","F"))) -> B | H17: =IF(Sheet1!G13>=90,"A",IF(Sheet1!G13>=75,"B",IF(Sheet1!G13>=60,"C","F"))) -> B | I17: =IF(AVERAGE(Sheet1!E13:G13)>=90,"A",IF(AVERAGE(Sheet1!E13:G13)>=75,"B",IF(AVERAGE(Sheet1!E13:G13)>=60,"C","F"))) -> B | J17: =IF(Sheet1!N13>30000,"10% Discount","No Discount") -> 10% Discount
... A25: =Sheet1!C21 -> 1020 | B25: =Sheet1!D21 -> Student 20 | C25: =Sheet1!E21 -> 83 | D25: =Sheet1!F21 -> 92 | E25: =Sheet1!G21 -> 55 | F25: =IF(Sheet1!E21>=90,"A",IF(Sheet1!E21>=75,"B",IF(Sheet1!E21>=60,"C","F"))) -> B | G25: =IF(Sheet1!F21>=90,"A",IF(Sheet1!F21>=75,"B",IF(Sheet1!F21>=60,"C","F"))) -> A | H25: =IF(Sheet1!G21>=90,"A",IF(Sheet1!G21>=75,"B",IF(Sheet1!G21>=60,"C","F"))) -> F | I25: =IF(AVERAGE(Sheet1!E21:G21)>=90,"A",IF(AVERAGE(Sheet1!E21:G21)>=75,"B",IF(AVERAGE(Sheet1!E21:G21)>=60,"C","F"))) -> B | J25: =IF(Sheet1!N21>30000,"10% Discount","No Discount") -> 10% Discount
A27: TASK 2 — Use COUNTIFS to Count Students Scoring Above 60 (per subject & combined)
A28: Metric | B28: Formula | C28: Result | D28: Metric | E28: Formula | F28: Result | G28: Notes
A29: Math > 60 | B29: '=COUNTIFS(Sheet1!E2:E21,">60") | C29: =COUNTIFS(Sheet1!E2:E21,">60") -> 19 | D29: Science > 60 | E29: '=COUNTIFS(Sheet1!F2:F21,">60") | F29: =COUNTIFS(Sheet1!F2:F21,">60") -> 11 | G29: Count students where that subject score exceeds 60
A30: English > 60 | B30: '=COUNTIFS(Sheet1!G2:G21,">60") | C30: =COUNTIFS(Sheet1!G2:G21,">60") -> 10 | D30: Math AND Science >60 | E30: '=COUNTIFS(Sheet1!E2:E21,">60",Sheet1!F2:F21,">60") | F30: =COUNTIFS(Sheet1!E2:E21,">60",Sheet1!F2:F21,">60") -> 10 | G30: COUNTIFS with two criteria (AND logic)
A31: Math > 80 | B31: '=COUNTIFS(Sheet1!E2:E21,">80") | C31: =COUNTIFS(Sheet1!E2:E21,">80") -> 10 | D31: All 3 subjects > 60 | E31: '=COUNTIFS(Sheet1!E2:E21,">60",Sheet1!F2:F21,">60",Sheet1!G2:G21,">60") | F31: =COUNTIFS(Sheet1!E2:E21,">60",Sheet1!F2:F21,">60",Sheet1!G2:G21,">60") -> 6 | G31: All three subjects above 60 simultaneously
A32: Avg score > 60 | B32: '=COUNTIFS(Sheet1!E2:E21,">50") | C32: =COUNTIFS(Sheet1!E2:E21,">50") -> 19 | D32: IT Dept employees | E32: '=COUNTIFS(Sheet1!S2:S21,"IT") | F32: =COUNTIFS(Sheet1!S2:S21,"IT") -> 5 | G32: COUNTIFS on non-numeric data (department)
A34: TASK 3 — Use VLOOKUP to Find Product & Amount from Sales Data
A35: Lookup: Sales ID | B35: VLOOKUP — Product | C35: Result | D35: VLOOKUP — Region | E35: Result | F35: VLOOKUP — Salesperson | G35: Result | H35: VLOOKUP — Amount | I35: Result | J35: Notes
A36: 2001 | B36: '=VLOOKUP(2001,Sheet1!$J$2:$N$21,2,0) | C36: =VLOOKUP(2001,Sheet1!$J$2:$N$21,2,0) -> Keyboard | D36: '=VLOOKUP(2001,Sheet1!$J$2:$N$21,3,0) | E36: =VLOOKUP(2001,Sheet1!$J$2:$N$21,3,0) -> South | F36: '=VLOOKUP(2001,Sheet1!$J$2:$N$21,4,0) | G36: =VLOOKUP(2001,Sheet1!$J$2:$N$21,4,0) -> Person 1 | H36: '=VLOOKUP(2001,Sheet1!$J$2:$N$21,5,0) | I36: =VLOOKUP(2001,Sheet1!$J$2:$N$21,5,0) -> 7048 | J36: VLOOKUP(ID, $J$2:$N$21, col, 0) — col 2=Prod,3=Region,4=Person,5=Amt
A37: 2005 | B37: '=VLOOKUP(2005,Sheet1!$J$2:$N$21,2,0) | C37: =VLOOKUP(2005,Sheet1!$J$2:$N$21,2,0) -> Keyboard | D37: '=VLOOKUP(2005,Sheet1!$J$2:$N$21,3,0) | E37: =VLOOKUP(2005,Sheet1!$J$2:$N$21,3,0) -> North | F37: '=VLOOKUP(2005,Sheet1!$J$2:$N$21,4,0) | G37: =VLOOKUP(2005,Sheet1!$J$2:$N$21,4,0) -> Person 5 | H37: '=VLOOKUP(2005,Sheet1!$J$2:$N$21,5,0) | I37: =VLOOKUP(2005,Sheet1!$J$2:$N$21,5,0) -> 43388 | J37: VLOOKUP(ID, $J$2:$N$21, col, 0) — col 2=Prod,3=Region,4=Person,5=Amt
A38: 2009 | B38: '=VLOOKUP(2009,Sheet1!$J$2:$N$21,2,0) | C38: =VLOOKUP(2009,Sheet1!$J$2:$N$21,2,0) -> Printer | D38: '=VLOOKUP(2009,Sheet1!$J$2:$N$21,3,0) | E38: =VLOOKUP(2009,Sheet1!$J$2:$N$21,3,0) -> East | F38: '=VLOOKUP(2009,Sheet1!$J$2:$N$21,4,0) | G38: =VLOOKUP(2009,Sheet1!$J$2:$N$21,4,0) -> Person 9 | H38: '=VLOOKUP(2009,Sheet1!$J$2:$N$21,5,0) | I38: =VLOOKUP(2009,Sheet1!$J$2:$N$21,5,0) -> 19746 | J38: VLOOKUP(ID, $J$2:$N$21, col, 0) — col 2=Prod,3=Region,4=Person,5=Amt
A39: 2013 | B39: '=VLOOKUP(2013,Sheet1!$J$2:$N$21,2,0) | C39: =VLOOKUP(2013,Sheet1!$J$2:$N$21,2,0) -> Laptop | D39: '=VLOOKUP(2013,Sheet1!$J$2:$N$21,3,0) | E39: =VLOOKUP(2013,Sheet1!$J$2:$N$21,3,0) -> East | F39: '=VLOOKUP(2013,Sheet1!$J$2:$N$21,4,0) | G39: =VLOOKUP(2013,Sheet1!$J$2:$N$21,4,0) -> Person 13 | H39: '=VLOOKUP(2013,Sheet1!$J$2:$N$21,5,0) | I39: =VLOOKUP(2013,Sheet1!$J$2:$N$21,5,0) -> 15560 | J39: VLOOKUP(ID, $J$2:$N$21, col, 0) — col 2=Prod,3=Region,4=Person,5=Amt
A40: 2017 | B40: '=VLOOKUP(2017,Sheet1!$J$2:$N$21,2,0) | C40: =VLOOKUP(2017,Sheet1!$J$2:$N$21,2,0) -> Monitor | D40: '=VLOOKUP(2017,Sheet1!$J$2:$N$21,3,0) | E40: =VLOOKUP(2017,Sheet1!$J$2:$N$21,3,0) -> North | F40: '=VLOOKUP(2017,Sheet1!$J$2:$N$21,4,0) | G40: =VLOOKUP(2017,Sheet1!$J$2:$N$21,4,0) -> Person 17 | H40: '=VLOOKUP(2017,Sheet1!$J$2:$N$21,5,0) | I40: =VLOOKUP(2017,Sheet1!$J$2:$N$21,5,0) -> 41871 | J40: VLOOKUP(ID, $J$2:$N$21, col, 0) — col 2=Prod,3=Region,4=Person,5=Amt
A41: 2020 | B41: '=VLOOKUP(2020,Sheet1!$J$2:$N$21,2,0) | C41: =VLOOKUP(2020,Sheet1!$J$2:$N$21,2,0) -> Printer | D41: '=VLOOKUP(2020,Sheet1!$J$2:$N$21,3,0) | E41: =VLOOKUP(2020,Sheet1!$J$2:$N$21,3,0) -> West | F41: '=VLOOKUP(2020,Sheet1!$J$2:$N$21,4,0) | G41: =VLOOKUP(2020,Sheet1!$J$2:$N$21,4,0) -> Person 20 | H41: '=VLOOKUP(2020,Sheet1!$J$2:$N$21,5,0) | I41: =VLOOKUP(2020,Sheet1!$J$2:$N$21,5,0) -> 33953 | J41: VLOOKUP(ID, $J$2:$N$21, col, 0) — col 2=Prod,3=Region,4=Person,5=Amt
A43: TASK 4 — Apply XLOOKUP to Fetch Employee Salaries Dynamically (via INDEX/MATCH for compatibility)
A44: Employee Name | B44: XLOOKUP Formula (Excel 365) | C44: Department | D44: Salary Result | E44: INDEX/MATCH Equiv. | F44: Salary (I/M) | G44: Notes
A45: Employee 1 | B45: '=XLOOKUP("Employee 1",Sheet1!$R$2:$R$21,Sheet1!$T$2:$T$21) | C45: =INDEX(Sheet1!$S$2:$S$21,MATCH("Employee 1",Sheet1!$R$2:$R$21,0)) -> Finance | D45: =INDEX(Sheet1!$T$2:$T$21,MATCH("Employee 1",Sheet1!$R$2:$R$21,0)) -> 86766 | E45: '=INDEX($T$2:$T$21,MATCH("Employee 1",$R$2:$R$21,0)) | F45: =INDEX(Sheet1!$T$2:$T$21,MATCH("Employee 1",Sheet1!$R$2:$R$21,0)) -> 86766 | G45: XLOOKUP searches lookup_array & returns result_array value — no col index needed
A46: Employee 3 | B46: '=XLOOKUP("Employee 3",Sheet1!$R$2:$R$21,Sheet1!$T$2:$T$21) | C46: =INDEX(Sheet1!$S$2:$S$21,MATCH("Employee 3",Sheet1!$R$2:$R$21,0)) -> HR | D46: =INDEX(Sheet1!$T$2:$T$21,MATCH("Employee 3",Sheet1!$R$2:$R$21,0)) -> 63374 | E46: '=INDEX($T$2:$T$21,MATCH("Employee 3",$R$2:$R$21,0)) | F46: =INDEX(Sheet1!$T$2:$T$21,MATCH("Employee 3",Sheet1!$R$2:$R$21,0)) -> 63374 | G46: XLOOKUP searches lookup_array & returns result_array value — no col index needed
A47: Employee 5 | B47: '=XLOOKUP("Employee 5",Sheet1!$R$2:$R$21,Sheet1!$T$2:$T$21) | C47: =INDEX(Sheet1!$S$2:$S$21,MATCH("Employee 5",Sheet1!$R$2:$R$21,0)) -> IT | D47: =INDEX(Sheet1!$T$2:$T$21,MATCH("Employee 5",Sheet1!$R$2:$R$21,0)) -> 54149 | E47: '=INDEX($T$2:$T$21,MATCH("Employee 5",$R$2:$R$21,0)) | F47: =INDEX(Sheet1!$T$2:$T$21,MATCH("Employee 5",Sheet1!$R$2:$R$21,0)) -> 54149 | G47: XLOOKUP searches lookup_array & returns result_array value — no col index needed
A48: Employee 7 | B48: '=XLOOKUP("Employee 7",Sheet1!$R$2:$R$21,Sheet1!$T$2:$T$21) | C48: =INDEX(Sheet1!$S$2:$S$21,MATCH("Employee 7",Sheet1!$R$2:$R$21,0)) -> Marketing | D48: =INDEX(Sheet1!$T$2:$T$21,MATCH("Employee 7",Sheet1!$R$2:$R$21,0)) -> 35960 | E48: '=INDEX($T$2:$T$21,MATCH("Employee 7",$R$2:$R$21,0)) | F48: =INDEX(Sheet1!$T$2:$T$21,MATCH("Employee 7",Sheet1!$R$2:$R$21,0)) -> 35960 | G48: XLOOKUP searches lookup_array & returns result_array value — no col index needed
A49: Employee 9 | B49: '=XLOOKUP("Employee 9",Sheet1!$R$2:$R$21,Sheet1!$T$2:$T$21) | C49: =INDEX(Sheet1!$S$2:$S$21,MATCH("Employee 9",Sheet1!$R$2:$R$21,0)) -> IT | D49: =INDEX(Sheet1!$T$2:$T$21,MATCH("Employee 9",Sheet1!$R$2:$R$21,0)) -> 90423 | E49: '=INDEX($T$2:$T$21,MATCH("Employee 9",$R$2:$R$21,0)) | F49: =INDEX(Sheet1!$T$2:$T$21,MATCH("Employee 9",Sheet1!$R$2:$R$21,0)) -> 90423 | G49: XLOOKUP searches lookup_array & returns result_array value — no col index needed
A50: Employee 11 | B50: '=XLOOKUP("Employee 11",Sheet1!$R$2:$R$21,Sheet1!$T$2:$T$21) | C50: =INDEX(Sheet1!$S$2:$S$21,MATCH("Employee 11",Sheet1!$R$2:$R$21,0)) -> Finance | D50: =INDEX(Sheet1!$T$2:$T$21,MATCH("Employee 11",Sheet1!$R$2:$R$21,0)) -> 107634 | E50: '=INDEX($T$2:$T$21,MATCH("Employee 11",$R$2:$R$21,0)) | F50: =INDEX(Sheet1!$T$2:$T$21,MATCH("Employee 11",Sheet1!$R$2:$R$21,0)) -> 107634 | G50: XLOOKUP searches lookup_array & returns result_array value — no col index needed
A51: Employee 13 | B51: '=XLOOKUP("Employee 13",Sheet1!$R$2:$R$21,Sheet1!$T$2:$T$21) | C51: =INDEX(Sheet1!$S$2:$S$21,MATCH("Employee 13",Sheet1!$R$2:$R$21,0)) -> HR | D51: =INDEX(Sheet1!$T$2:$T$21,MATCH("Employee 13",Sheet1!$R$2:$R$21,0)) -> 40872 | E51: '=INDEX($T$2:$T$21,MATCH("Employee 13",$R$2:$R$21,0)) | F51: =INDEX(Sheet1!$T$2:$T$21,MATCH("Employee 13",Sheet1!$R$2:$R$21,0)) -> 40872 | G51: XLOOKUP searches lookup_array & returns result_array value — no col index needed
A52: Employee 15 | B52: '=XLOOKUP("Employee 15",Sheet1!$R$2:$R$21,Sheet1!$T$2:$T$21) | C52: =INDEX(Sheet1!$S$2:$S$21,MATCH("Employee 15",Sheet1!$R$2:$R$21,0)) -> HR | D52: =INDEX(Sheet1!$T$2:$T$21,MATCH("Employee 15",Sheet1!$R$2:$R$21,0)) -> 63297 | E52: '=INDEX($T$2:$T$21,MATCH("Employee 15",$R$2:$R$21,0)) | F52: =INDEX(Sheet1!$T$2:$T$21,MATCH("Employee 15",Sheet1!$R$2:$R$21,0)) -> 63297 | G52: XLOOKUP searches lookup_array & returns result_array value — no col index needed
A53: Employee 17 | B53: '=XLOOKUP("Employee 17",Sheet1!$R$2:$R$21,Sheet1!$T$2:$T$21) | C53: =INDEX(Sheet1!$S$2:$S$21,MATCH("Employee 17",Sheet1!$R$2:$R$21,0)) -> HR | D53: =INDEX(Sheet1!$T$2:$T$21,MATCH("Employee 17",Sheet1!$R$2:$R$21,0)) -> 86915 | E53: '=INDEX($T$2:$T$21,MATCH("Employee 17",$R$2:$R$21,0)) | F53: =INDEX(Sheet1!$T$2:$T$21,MATCH("Employee 17",Sheet1!$R$2:$R$21,0)) -> 86915 | G53: XLOOKUP searches lookup_array & returns result_array value — no col index needed
A54: Employee 19 | B54: '=XLOOKUP("Employee 19",Sheet1!$R$2:$R$21,Sheet1!$T$2:$T$21) | C54: =INDEX(Sheet1!$S$2:$S$21,MATCH("Employee 19",Sheet1!$R$2:$R$21,0)) -> Marketing | D54: =INDEX(Sheet1!$T$2:$T$21,MATCH("Employee 19",Sheet1!$R$2:$R$21,0)) -> 116283 | E54: '=INDEX($T$2:$T$21,MATCH("Employee 19",$R$2:$R$21,0)) | F54: =INDEX(Sheet1!$T$2:$T$21,MATCH("Employee 19",Sheet1!$R$2:$R$21,0)) -> 116283 | G54: XLOOKUP searches lookup_array & returns result_array value — no col index needed
A56: TASK 5 — Format and Analyze Date of Joining in Employee Data
A57: Employee | B57: Joining Date (DD-MMM-YYYY) | C57: Year Joined | D57: Month Name | E57: Day of Week | F57: Years of Service | G57: Months Served | H57: Days Served | I57: Quarter Joined | J57: Status
A58: =Sheet1!R2 -> Employee 1 | B58: =Sheet1!U2 -> 42005 | C58: =YEAR(Sheet1!U2) -> 2015 | D58: =TEXT(Sheet1!U2,"MMMM") -> January | E58: =TEXT(Sheet1!U2,"DDDD") -> Thursday | F58: =IF(Sheet1!U2>TODAY(),"Future",DATEDIF(Sheet1!U2,TODAY(),"Y")&" yrs") -> 11 yrs | G58: =IF(Sheet1!U2>TODAY(),"Future",DATEDIF(Sheet1!U2,TODAY(),"M")) -> 134 | H58: =IF(Sheet1!U2>TODAY(),"Future",INT(TODAY()-Sheet1!U2)) -> 4098 | I58: ="Q"&INT((MONTH(Sheet1!U2)-1)/3+1) -> Q1 | J58: =IF(Sheet1!U2>TODAY(),"Not Yet Joined",IF(DATEDIF(Sheet1!U2,TODAY(),"Y")>=5,"Senior","Junior")) -> Senior
A59: =Sheet1!R3 -> Employee 2 | B59: =Sheet1!U3 -> 42255 | C59: =YEAR(Sheet1!U3) -> 2015 | D59: =TEXT(Sheet1!U3,"MMMM") -> September | E59: =TEXT(Sheet1!U3,"DDDD") -> Tuesday | F59: =IF(Sheet1!U3>TODAY(),"Future",DATEDIF(Sheet1!U3,TODAY(),"Y")&" yrs") -> 10 yrs | G59: =IF(Sheet1!U3>TODAY(),"Future",DATEDIF(Sheet1!U3,TODAY(),"M")) -> 126 | H59: =IF(Sheet1!U3>TODAY(),"Future",INT(TODAY()-Sheet1!U3)) -> 3848 | I59: ="Q"&INT((MONTH(Sheet1!U3)-1)/3+1) -> Q3 | J59: =IF(Sheet1!U3>TODAY(),"Not Yet Joined",IF(DATEDIF(Sheet1!U3,TODAY(),"Y")>=5,"Senior","Junior")) -> Senior
A60: =Sheet1!R4 -> Employee 3 | B60: =Sheet1!U4 -> 42505 | C60: =YEAR(Sheet1!U4) -> 2016 | D60: =TEXT(Sheet1!U4,"MMMM") -> May | E60: =TEXT(Sheet1!U4,"DDDD") -> Sunday | F60: =IF(Sheet1!U4>TODAY(),"Future",DATEDIF(Sheet1!U4,TODAY(),"Y")&" yrs") -> 9 yrs | G60: =IF(Sheet1!U4>TODAY(),"Future",DATEDIF(Sheet1!U4,TODAY(),"M")) -> 118 | H60: =IF(Sheet1!U4>TODAY(),"Future",INT(TODAY()-Sheet1!U4)) -> 3598 | I60: ="Q"&INT((MONTH(Sheet1!U4)-1)/3+1) -> Q2 | J60: =IF(Sheet1!U4>TODAY(),"Not Yet Joined",IF(DATEDIF(Sheet1!U4,TODAY(),"Y")>=5,"Senior","Junior")) -> Senior
A61: =Sheet1!R5 -> Employee 4 | B61: =Sheet1!U5 -> 42755 | C61: =YEAR(Sheet1!U5) -> 2017 | D61: =TEXT(Sheet1!U5,"MMMM") -> January | E61: =TEXT(Sheet1!U5,"DDDD") -> Friday | F61: =IF(Sheet1!U5>TODAY(),"Future",DATEDIF(Sheet1!U5,TODAY(),"Y")&" yrs") -> 9 yrs | G61: =IF(Sheet1!U5>TODAY(),"Future",DATEDIF(Sheet1!U5,TODAY(),"M")) -> 110 | H61: =IF(Sheet1!U5>TODAY(),"Future",INT(TODAY()-Sheet1!U5)) -> 3348 | I61: ="Q"&INT((MONTH(Sheet1!U5)-1)/3+1) -> Q1 | J61: =IF(Sheet1!U5>TODAY(),"Not Yet Joined",IF(DATEDIF(Sheet1!U5,TODAY(),"Y")>=5,"Senior","Junior")) -> Senior
A62: =Sheet1!R6 -> Employee 5 | B62: =Sheet1!U6 -> 43005 | C62: =YEAR(Sheet1!U6) -> 2017 | D62: =TEXT(Sheet1!U6,"MMMM") -> September | E62: =TEXT(Sheet1!U6,"DDDD") -> Wednesday | F62: =IF(Sheet1!U6>TODAY(),"Future",DATEDIF(Sheet1!U6,TODAY(),"Y")&" yrs") -> 8 yrs | G62: =IF(Sheet1!U6>TODAY(),"Future",DATEDIF(Sheet1!U6,TODAY(),"M")) -> 101 | H62: =IF(Sheet1!U6>TODAY(),"Future",INT(TODAY()-Sheet1!U6)) -> 3098 | I62: ="Q"&INT((MONTH(Sheet1!U6)-1)/3+1) -> Q3 | J62: =IF(Sheet1!U6>TODAY(),"Not Yet Joined",IF(DATEDIF(Sheet1!U6,TODAY(),"Y")>=5,"Senior","Junior")) -> Senior
A63: =Sheet1!R7 -> Employee 6 | B63: =Sheet1!U7 -> 43255 | C63: =YEAR(Sheet1!U7) -> 2018 | D63: =TEXT(Sheet1!U7,"MMMM") -> June | E63: =TEXT(Sheet1!U7,"DDDD") -> Monday | F63: =IF(Sheet1!U7>TODAY(),"Future",DATEDIF(Sheet1!U7,TODAY(),"Y")&" yrs") -> 7 yrs | G63: =IF(Sheet1!U7>TODAY(),"Future",DATEDIF(Sheet1!U7,TODAY(),"M")) -> 93 | H63: =IF(Sheet1!U7>TODAY(),"Future",INT(TODAY()-Sheet1!U7)) -> 2848 | I63: ="Q"&INT((MONTH(Sheet1!U7)-1)/3+1) -> Q2 | J63: =IF(Sheet1!U7>TODAY(),"Not Yet Joined",IF(DATEDIF(Sheet1!U7,TODAY(),"Y")>=5,"Senior","Junior")) -> Senior
A64: =Sheet1!R8 -> Employee 7 | B64: =Sheet1!U8 -> 43505 | C64: =YEAR(Sheet1!U8) -> 2019 | D64: =TEXT(Sheet1!U8,"MMMM") -> February | E64: =TEXT(Sheet1!U8,"DDDD") -> Saturday | F64: =IF(Sheet1!U8>TODAY(),"Future",DATEDIF(Sheet1!U8,TODAY(),"Y")&" yrs") -> 7 yrs | G64: =IF(Sheet1!U8>TODAY(),"Future",DATEDIF(Sheet1!U8,TODAY(),"M")) -> 85 | H64: =IF(Sheet1!U8>TODAY(),"Future",INT(TODAY()-Sheet1!U8)) -> 2598 | I64: ="Q"&INT((MONTH(Sheet1!U8)-1)/3+1) -> Q1 | J64: =IF(Sheet1!U8>TODAY(),"Not Yet Joined",IF(DATEDIF(Sheet1!U8,TODAY(),"Y")>=5,"Senior","Junior")) -> Senior
A65: =Sheet1!R9 -> Employee 8 | B65: =Sheet1!U9 -> 43755 | C65: =YEAR(Sheet1!U9) -> 2019 | D65: =TEXT(Sheet1!U9,"MMMM") -> October | E65: =TEXT(Sheet1!U9,"DDDD") -> Thursday | F65: =IF(Sheet1!U9>TODAY(),"Future",DATEDIF(Sheet1!U9,TODAY(),"Y")&" yrs") -> 6 yrs | G65: =IF(Sheet1!U9>TODAY(),"Future",DATEDIF(Sheet1!U9,TODAY(),"M")) -> 77 | H65: =IF(Sheet1!U9>TODAY(),"Future",INT(TODAY()-Sheet1!U9)) -> 2348 | I65: ="Q"&INT((MONTH(Sheet1!U9)-1)/3+1) -> Q4 | J65: =IF(Sheet1!U9>TODAY(),"Not Yet Joined",IF(DATEDIF(Sheet1!U9,TODAY(),"Y")>=5,"Senior","Junior")) -> Senior
A66: =Sheet1!R10 -> Employee 9 | B66: =Sheet1!U10 -> 44005 | C66: =YEAR(Sheet1!U10) -> 2020 | D66: =TEXT(Sheet1!U10,"MMMM") -> June | E66: =TEXT(Sheet1!U10,"DDDD") -> Tuesday | F66: =IF(Sheet1!U10>TODAY(),"Future",DATEDIF(Sheet1!U10,TODAY(),"Y")&" yrs") -> 5 yrs | G66: =IF(Sheet1!U10>TODAY(),"Future",DATEDIF(Sheet1!U10,TODAY(),"M")) -> 68 | H66: =IF(Sheet1!U10>TODAY(),"Future",INT(TODAY()-Sheet1!U10)) -> 2098 | I66: ="Q"&INT((MONTH(Sheet1!U10)-1)/3+1) -> Q2 | J66: =IF(Sheet1!U10>TODAY(),"Not Yet Joined",IF(DATEDIF(Sheet1!U10,TODAY(),"Y")>=5,"Senior","Junior")) -> Senior
A67: =Sheet1!R11 -> Employee 10 | B67: =Sheet1!U11 -> 44255 | C67: =YEAR(Sheet1!U11) -> 2021 | D67: =TEXT(Sheet1!U11,"MMMM") -> February | E67: =TEXT(Sheet1!U11,"DDDD") -> Sunday | F67: =IF(Sheet1!U11>TODAY(),"Future",DATEDIF(Sheet1!U11,TODAY(),"Y")&" yrs") -> 5 yrs | G67: =IF(Sheet1!U11>TODAY(),"Future",DATEDIF(Sheet1!U11,TODAY(),"M")) -> 60 | H67: =IF(Sheet1!U11>TODAY(),"Future",INT(TODAY()-Sheet1!U11)) -> 1848 | I67: ="Q"&INT((MONTH(Sheet1!U11)-1)/3+1) -> Q1 | J67: =IF(Sheet1!U11>TODAY(),"Not Yet Joined",IF(DATEDIF(Sheet1!U11,TODAY(),"Y")>=5,"Senior","Junior")) -> Senior
A68: =Sheet1!R12 -> Employee 11 | B68: =Sheet1!U12 -> 44505 | C68: =YEAR(Sheet1!U12) -> 2021 | D68: =TEXT(Sheet1!U12,"MMMM") -> November | E68: =TEXT(Sheet1!U12,"DDDD") -> Friday | F68: =IF(Sheet1!U12>TODAY(),"Future",DATEDIF(Sheet1!U12,TODAY(),"Y")&" yrs") -> 4 yrs | G68: =IF(Sheet1!U12>TODAY(),"Future",DATEDIF(Sheet1!U12,TODAY(),"M")) -> 52 | H68: =IF(Sheet1!U12>TODAY(),"Future",INT(TODAY()-Sheet1!U12)) -> 1598 | I68: ="Q"&INT((MONTH(Sheet1!U12)-1)/3+1) -> Q4 | J68: =IF(Sheet1!U12>TODAY(),"Not Yet Joined",IF(DATEDIF(Sheet1!U12,TODAY(),"Y")>=5,"Senior","Junior")) -> Junior
A69: =Sheet1!R13 -> Employee 12 | B69: =Sheet1!U13 -> 44755 | C69: =YEAR(Sheet1!U13) -> 2022 | D69: =TEXT(Sheet1!U13,"MMMM") -> July | E69: =TEXT(Sheet1!U13,"DDDD") -> Wednesday | F69: =IF(Sheet1!U13>TODAY(),"Future",DATEDIF(Sheet1!U13,TODAY(),"Y")&" yrs") -> 3 yrs | G69: =IF(Sheet1!U13>TODAY(),"Future",DATEDIF(Sheet1!U13,TODAY(),"M")) -> 44 | H69: =IF(Sheet1!U13>TODAY(),"Future",INT(TODAY()-Sheet1!U13)) -> 1348 | I69: ="Q"&INT((MONTH(Sheet1!U13)-1)/3+1) -> Q3 | J69: =IF(Sheet1!U13>TODAY(),"Not Yet Joined",IF(DATEDIF(Sheet1!U13,TODAY(),"Y")>=5,"Senior","Junior")) -> Junior
... A77: =Sheet1!R21 -> Employee 20 | B77: =Sheet1!U21 -> 46755 | C77: =YEAR(Sheet1!U21) -> 2028 | D77: =TEXT(Sheet1!U21,"MMMM") -> January | E77: =TEXT(Sheet1!U21,"DDDD") -> Monday | F77: =IF(Sheet1!U21>TODAY(),"Future",DATEDIF(Sheet1!U21,TODAY(),"Y")&" yrs") -> Future | G77: =IF(Sheet1!U21>TODAY(),"Future",DATEDIF(Sheet1!U21,TODAY(),"M")) -> Future | H77: =IF(Sheet1!U21>TODAY(),"Future",INT(TODAY()-Sheet1!U21)) -> Future | I77: ="Q"&INT((MONTH(Sheet1!U21)-1)/3+1) -> Q1 | J77: =IF(Sheet1!U21>TODAY(),"Not Yet Joined",IF(DATEDIF(Sheet1!U21,TODAY(),"Y")>=5,"Senior","Junior")) -> Not Yet Joined
A79: TASK 6 — Use FILTER Function to Extract Students with Grades Above 80 (Math)
A80: 🎓 Students: Math Score > 80 | F80: 💰 Sales: Amount > 30,000
A81: Formula: =FILTER(Sheet1!C2:G21, Sheet1!E2:E21>80) | F81: Formula: =FILTER(Sheet1!J2:N21, Sheet1!N2:N21>30000)
A82: Student ID | B82: Name | C82: Math | D82: Science | E82: English | F82: Sales ID | G82: Product | H82: Region | I82: Salesperson | J82: Amount
A83: =Sheet1!C4 -> 1003 | B83: =Sheet1!D4 -> Student 3 | C83: =Sheet1!E4 -> 97 | D83: =Sheet1!F4 -> 60 | E83: =Sheet1!G4 -> 51 | F83: =Sheet1!J6 -> 2005 | G83: =Sheet1!K6 -> Keyboard | H83: =Sheet1!L6 -> North | I83: =Sheet1!M6 -> Person 5 | J83: =Sheet1!N6 -> 43388
A84: =Sheet1!C9 -> 1008 | B84: =Sheet1!D9 -> Student 8 | C84: =Sheet1!E9 -> 94 | D84: =Sheet1!F9 -> 67 | E84: =Sheet1!G9 -> 64 | F84: =Sheet1!J8 -> 2007 | G84: =Sheet1!K8 -> Mouse | H84: =Sheet1!L8 -> East | I84: =Sheet1!M8 -> Person 7 | J84: =Sheet1!N8 -> 32058
A85: =Sheet1!C11 -> 1010 | B85: =Sheet1!D11 -> Student 10 | C85: =Sheet1!E11 -> 98 | D85: =Sheet1!F11 -> 54 | E85: =Sheet1!G11 -> 58 | F85: =Sheet1!J9 -> 2008 | G85: =Sheet1!K9 -> Keyboard | H85: =Sheet1!L9 -> East | I85: =Sheet1!M9 -> Person 8 | J85: =Sheet1!N9 -> 46429
A86: =Sheet1!C13 -> 1012 | B86: =Sheet1!D13 -> Student 12 | C86: =Sheet1!E13 -> 85 | D86: =Sheet1!F13 -> 89 | E86: =Sheet1!G13 -> 79 | F86: =Sheet1!J11 -> 2010 | G86: =Sheet1!K11 -> Keyboard | H86: =Sheet1!L11 -> South | I86: =Sheet1!M11 -> Person 10 | J86: =Sheet1!N11 -> 35185
A87: =Sheet1!C14 -> 1013 | B87: =Sheet1!D14 -> Student 13 | C87: =Sheet1!E14 -> 98 | D87: =Sheet1!F14 -> 90 | E87: =Sheet1!G14 -> 97 | F87: =Sheet1!J12 -> 2011 | G87: =Sheet1!K12 -> Keyboard | H87: =Sheet1!L12 -> East | I87: =Sheet1!M12 -> Person 11 | J87: =Sheet1!N12 -> 33920
A88: =Sheet1!C15 -> 1014 | B88: =Sheet1!D15 -> Student 14 | C88: =Sheet1!E15 -> 93 | D88: =Sheet1!F15 -> 40 | E88: =Sheet1!G15 -> 44 | F88: =Sheet1!J13 -> 2012 | G88: =Sheet1!K13 -> Monitor | H88: =Sheet1!L13 -> North | I88: =Sheet1!M13 -> Person 12 | J88: =Sheet1!N13 -> 35611
A89: =Sheet1!C17 -> 1016 | B89: =Sheet1!D17 -> Student 16 | C89: =Sheet1!E17 -> 98 | D89: =Sheet1!F17 -> 77 | E89: =Sheet1!G17 -> 60 | F89: =Sheet1!J18 -> 2017 | G89: =Sheet1!K18 -> Monitor | H89: =Sheet1!L18 -> North | I89: =Sheet1!M18 -> Person 17 | J89: =Sheet1!N18 -> 41871
A90: =Sheet1!C19 -> 1018 | B90: =Sheet1!D19 -> Student 18 | C90: =Sheet1!E19 -> 82 | D90: =Sheet1!F19 -> 48 | E90: =Sheet1!G19 -> 79 | F90: =Sheet1!J19 -> 2018 | G90: =Sheet1!K19 -> Monitor | H90: =Sheet1!L19 -> West | I90: =Sheet1!M19 -> Person 18 | J90: =Sheet1!N19 -> 38161
A91: =Sheet1!C20 -> 1019 | B91: =Sheet1!D20 -> Student 19 | C91: =Sheet1!E20 -> 90 | D91: =Sheet1!F20 -> 78 | E91: =Sheet1!G20 -> 60 | F91: =Sheet1!J20 -> 2019 | G91: =Sheet1!K20 -> Mouse | H91: =Sheet1!L20 -> West | I91: =Sheet1!M20 -> Person 19 | J91: =Sheet1!N20 -> 30436
A92: =Sheet1!C21 -> 1020 | B92: =Sheet1!D21 -> Student 20 | C92: =Sheet1!E21 -> 83 | D92: =Sheet1!F21 -> 92 | E92: =Sheet1!G21 -> 55 | F92: =Sheet1!J21 -> 2020 | G92: =Sheet1!K21 -> Printer | H92: =Sheet1!L21 -> West | I92: =Sheet1!M21 -> Person 20 | J92: =Sheet1!N21 -> 33953
A94: Total students (Math > 80): | C94: =COUNTIF(Sheet1!E2:E21,">80") -> 10 | F94: Total sales (Amount > 30,000): | H94: =COUNTIF(Sheet1!N2:N21,">30000") -> 10
A95: Avg Math score (filtered group): | C95: =AVERAGEIF(Sheet1!E2:E21,">80") -> 91.8 | F95: Total Sales Amount (>30k): | H95: =SUMIF(Sheet1!N2:N21,">30000") -> 371012

Sheet Solutions
A1: PR.1 Fundamental Booster – All Task Solutions
A3: 1. IF Formulas – Grade Classification (>= 90 A, >= 75 B, >= 60 C, else F)
A4: Student ID | B4: Name | C4: Math | D4: Science | E4: English | F4: Grade (Math)
A5: =Sheet1!C2 -> 1001 | B5: =Sheet1!D2 -> Student 1 | C5: =Sheet1!E2 -> 61 | D5: =Sheet1!F2 -> 48 | E5: =Sheet1!G2 -> 76 | F5: =IF(Sheet1!E2>=90,"A",IF(Sheet1!E2>=75,"B",IF(Sheet1!E2>=60,"C","F"))) -> C
A6: =Sheet1!C3 -> 1002 | B6: =Sheet1!D3 -> Student 2 | C6: =Sheet1!E3 -> 78 | D6: =Sheet1!F3 -> 76 | E6: =Sheet1!G3 -> 70 | F6: =IF(Sheet1!E3>=90,"A",IF(Sheet1!E3>=75,"B",IF(Sheet1!E3>=60,"C","F"))) -> B
A7: =Sheet1!C4 -> 1003 | B7: =Sheet1!D4 -> Student 3 | C7: =Sheet1!E4 -> 97 | D7: =Sheet1!F4 -> 60 | E7: =Sheet1!G4 -> 51 | F7: =IF(Sheet1!E4>=90,"A",IF(Sheet1!E4>=75,"B",IF(Sheet1!E4>=60,"C","F"))) -> A
A8: =Sheet1!C5 -> 1004 | B8: =Sheet1!D5 -> Student 4 | C8: =Sheet1!E5 -> 74 | D8: =Sheet1!F5 -> 55 | E8: =Sheet1!G5 -> 46 | F8: =IF(Sheet1!E5>=90,"A",IF(Sheet1!E5>=75,"B",IF(Sheet1!E5>=60,"C","F"))) -> C
A9: =Sheet1!C6 -> 1005 | B9: =Sheet1!D6 -> Student 5 | C9: =Sheet1!E6 -> 68 | D9: =Sheet1!F6 -> 74 | E9: =Sheet1!G6 -> 84 | F9: =IF(Sheet1!E6>=90,"A",IF(Sheet1!E6>=75,"B",IF(Sheet1!E6>=60,"C","F"))) -> C
A10: =Sheet1!C7 -> 1006 | B10: =Sheet1!D7 -> Student 6 | C10: =Sheet1!E7 -> 80 | D10: =Sheet1!F7 -> 70 | E10: =Sheet1!G7 -> 65 | F10: =IF(Sheet1!E7>=90,"A",IF(Sheet1!E7>=75,"B",IF(Sheet1!E7>=60,"C","F"))) -> B
A11: =Sheet1!C8 -> 1007 | B11: =Sheet1!D8 -> Student 7 | C11: =Sheet1!E8 -> 75 | D11: =Sheet1!F8 -> 47 | E11: =Sheet1!G8 -> 78 | F11: =IF(Sheet1!E8>=90,"A",IF(Sheet1!E8>=75,"B",IF(Sheet1!E8>=60,"C","F"))) -> B
A12: =Sheet1!C9 -> 1008 | B12: =Sheet1!D9 -> Student 8 | C12: =Sheet1!E9 -> 94 | D12: =Sheet1!F9 -> 67 | E12: =Sheet1!G9 -> 64 | F12: =IF(Sheet1!E9>=90,"A",IF(Sheet1!E9>=75,"B",IF(Sheet1!E9>=60,"C","F"))) -> A
A13: =Sheet1!C10 -> 1009 | B13: =Sheet1!D10 -> Student 9 | C13: =Sheet1!E10 -> 41 | D13: =Sheet1!F10 -> 75 | E13: =Sheet1!G10 -> 56 | F13: =IF(Sheet1!E10>=90,"A",IF(Sheet1!E10>=75,"B",IF(Sheet1!E10>=60,"C","F"))) -> F
A14: =Sheet1!C11 -> 1010 | B14: =Sheet1!D11 -> Student 10 | C14: =Sheet1!E11 -> 98 | D14: =Sheet1!F11 -> 54 | E14: =Sheet1!G11 -> 58 | F14: =IF(Sheet1!E11>=90,"A",IF(Sheet1!E11>=75,"B",IF(Sheet1!E11>=60,"C","F"))) -> A
A15: =Sheet1!C12 -> 1011 | B15: =Sheet1!D12 -> Student 11 | C15: =Sheet1!E12 -> 73 | D15: =Sheet1!F12 -> 79 | E15: =Sheet1!G12 -> 53 | F15: =IF(Sheet1!E12>=90,"A",IF(Sheet1!E12>=75,"B",IF(Sheet1!E12>=60,"C","F"))) -> C
A16: =Sheet1!C13 -> 1012 | B16: =Sheet1!D13 -> Student 12 | C16: =Sheet1!E13 -> 85 | D16: =Sheet1!F13 -> 89 | E16: =Sheet1!G13 -> 79 | F16: =IF(Sheet1!E13>=90,"A",IF(Sheet1!E13>=75,"B",IF(Sheet1!E13>=60,"C","F"))) -> B
... A24: =Sheet1!C21 -> 1020 | B24: =Sheet1!D21 -> Student 20 | C24: =Sheet1!E21 -> 83 | D24: =Sheet1!F21 -> 92 | E24: =Sheet1!G21 -> 55 | F24: =IF(Sheet1!E21>=90,"A",IF(Sheet1!E21>=75,"B",IF(Sheet1!E21>=60,"C","F"))) -> B
A26: 2. IF with AND – Students scoring > 80 in BOTH Math AND Science
A27: Student ID | B27: Name | C27: Math | D27: Science | E27: English | F27: Both > 80?
A28: =Sheet1!C2 -> 1001 | B28: =Sheet1!D2 -> Student 1 | C28: =Sheet1!E2 -> 61 | D28: =Sheet1!F2 -> 48 | E28: =Sheet1!G2 -> 76 | F28: =IF(AND(Sheet1!E2>80,Sheet1!F2>80),"Yes","No") -> No
A29: =Sheet1!C3 -> 1002 | B29: =Sheet1!D3 -> Student 2 | C29: =Sheet1!E3 -> 78 | D29: =Sheet1!F3 -> 76 | E29: =Sheet1!G3 -> 70 | F29: =IF(AND(Sheet1!E3>80,Sheet1!F3>80),"Yes","No") -> No
A30: =Sheet1!C4 -> 1003 | B30: =Sheet1!D4 -> Student 3 | C30: =Sheet1!E4 -> 97 | D30: =Sheet1!F4 -> 60 | E30: =Sheet1!G4 -> 51 | F30: =IF(AND(Sheet1!E4>80,Sheet1!F4>80),"Yes","No") -> No
A31: =Sheet1!C5 -> 1004 | B31: =Sheet1!D5 -> Student 4 | C31: =Sheet1!E5 -> 74 | D31: =Sheet1!F5 -> 55 | E31: =Sheet1!G5 -> 46 | F31: =IF(AND(Sheet1!E5>80,Sheet1!F5>80),"Yes","No") -> No
A32: =Sheet1!C6 -> 1005 | B32: =Sheet1!D6 -> Student 5 | C32: =Sheet1!E6 -> 68 | D32: =Sheet1!F6 -> 74 | E32: =Sheet1!G6 -> 84 | F32: =IF(AND(Sheet1!E6>80,Sheet1!F6>80),"Yes","No") -> No
A33: =Sheet1!C7 -> 1006 | B33: =Sheet1!D7 -> Student 6 | C33: =Sheet1!E7 -> 80 | D33: =Sheet1!F7 -> 70 | E33: =Sheet1!G7 -> 65 | F33: =IF(AND(Sheet1!E7>80,Sheet1!F7>80),"Yes","No") -> No
A34: =Sheet1!C8 -> 1007 | B34: =Sheet1!D8 -> Student 7 | C34: =Sheet1!E8 -> 75 | D34: =Sheet1!F8 -> 47 | E34: =Sheet1!G8 -> 78 | F34: =IF(AND(Sheet1!E8>80,Sheet1!F8>80),"Yes","No") -> No
A35: =Sheet1!C9 -> 1008 | B35: =Sheet1!D9 -> Student 8 | C35: =Sheet1!E9 -> 94 | D35: =Sheet1!F9 -> 67 | E35: =Sheet1!G9 -> 64 | F35: =IF(AND(Sheet1!E9>80,Sheet1!F9>80),"Yes","No") -> No
A36: =Sheet1!C10 -> 1009 | B36: =Sheet1!D10 -> Student 9 | C36: =Sheet1!E10 -> 41 | D36: =Sheet1!F10 -> 75 | E36: =Sheet1!G10 -> 56 | F36: =IF(AND(Sheet1!E10>80,Sheet1!F10>80),"Yes","No") -> No
A37: =Sheet1!C11 -> 1010 | B37: =Sheet1!D11 -> Student 10 | C37: =Sheet1!E11 -> 98 | D37: =Sheet1!F11 -> 54 | E37: =Sheet1!G11 -> 58 | F37: =IF(AND(Sheet1!E11>80,Sheet1!F11>80),"Yes","No") -> No
A38: =Sheet1!C12 -> 1011 | B38: =Sheet1!D12 -> Student 11 | C38: =Sheet1!E12 -> 73 | D38: =Sheet1!F12 -> 79 | E38: =Sheet1!G12 -> 53 | F38: =IF(AND(Sheet1!E12>80,Sheet1!F12>80),"Yes","No") -> No
A39: =Sheet1!C13 -> 1012 | B39: =Sheet1!D13 -> Student 12 | C39: =Sheet1!E13 -> 85 | D39: =Sheet1!F13 -> 89 | E39: =Sheet1!G13 -> 79 | F39: =IF(AND(Sheet1!E13>80,Sheet1!F13>80),"Yes","No") -> Yes
... A47: =Sheet1!C21 -> 1020 | B47: =Sheet1!D21 -> Student 20 | C47: =Sheet1!E21 -> 83 | D47: =Sheet1!F21 -> 92 | E47: =Sheet1!G21 -> 55 | F47: =IF(AND(Sheet1!E21>80,Sheet1!F21>80),"Yes","No") -> Yes
A49: 3. IF with OR – Discount Eligibility (Amount > 40000 OR Product = Laptop)
A50: Sales ID | B50: Product | C50: Region | D50: Salesperson | E50: Amount | F50: Discount Eligible?
A51: =Sheet1!J2 -> 2001 | B51: =Sheet1!K2 -> Keyboard | C51: =Sheet1!L2 -> South | D51: =Sheet1!M2 -> Person 1 | E51: =Sheet1!N2 -> 7048 | F51: =IF(OR(Sheet1!N2>40000,Sheet1!K2="Laptop"),"Yes","No") -> No
A52: =Sheet1!J3 -> 2002 | B52: =Sheet1!K3 -> Printer | C52: =Sheet1!L3 -> West | D52: =Sheet1!M3 -> Person 2 | E52: =Sheet1!N3 -> 17428 | F52: =IF(OR(Sheet1!N3>40000,Sheet1!K3="Laptop"),"Yes","No") -> No
A53: =Sheet1!J4 -> 2003 | B53: =Sheet1!K4 -> Mouse | C53: =Sheet1!L4 -> South | D53: =Sheet1!M4 -> Person 3 | E53: =Sheet1!N4 -> 23672 | F53: =IF(OR(Sheet1!N4>40000,Sheet1!K4="Laptop"),"Yes","No") -> No
A54: =Sheet1!J5 -> 2004 | B54: =Sheet1!K5 -> Printer | C54: =Sheet1!L5 -> East | D54: =Sheet1!M5 -> Person 4 | E54: =Sheet1!N5 -> 5264 | F54: =IF(OR(Sheet1!N5>40000,Sheet1!K5="Laptop"),"Yes","No") -> No
A55: =Sheet1!J6 -> 2005 | B55: =Sheet1!K6 -> Keyboard | C55: =Sheet1!L6 -> North | D55: =Sheet1!M6 -> Person 5 | E55: =Sheet1!N6 -> 43388 | F55: =IF(OR(Sheet1!N6>40000,Sheet1!K6="Laptop"),"Yes","No") -> Yes
A56: =Sheet1!J7 -> 2006 | B56: =Sheet1!K7 -> Mouse | C56: =Sheet1!L7 -> North | D56: =Sheet1!M7 -> Person 6 | E56: =Sheet1!N7 -> 19757 | F56: =IF(OR(Sheet1!N7>40000,Sheet1!K7="Laptop"),"Yes","No") -> No
A57: =Sheet1!J8 -> 2007 | B57: =Sheet1!K8 -> Mouse | C57: =Sheet1!L8 -> East | D57: =Sheet1!M8 -> Person 7 | E57: =Sheet1!N8 -> 32058 | F57: =IF(OR(Sheet1!N8>40000,Sheet1!K8="Laptop"),"Yes","No") -> No
A58: =Sheet1!J9 -> 2008 | B58: =Sheet1!K9 -> Keyboard | C58: =Sheet1!L9 -> East | D58: =Sheet1!M9 -> Person 8 | E58: =Sheet1!N9 -> 46429 | F58: =IF(OR(Sheet1!N9>40000,Sheet1!K9="Laptop"),"Yes","No") -> Yes
A59: =Sheet1!J10 -> 2009 | B59: =Sheet1!K10 -> Printer | C59: =Sheet1!L10 -> East | D59: =Sheet1!M10 -> Person 9 | E59: =Sheet1!N10 -> 19746 | F59: =IF(OR(Sheet1!N10>40000,Sheet1!K10="Laptop"),"Yes","No") -> No
A60: =Sheet1!J11 -> 2010 | B60: =Sheet1!K11 -> Keyboard | C60: =Sheet1!L11 -> South | D60: =Sheet1!M11 -> Person 10 | E60: =Sheet1!N11 -> 35185 | F60: =IF(OR(Sheet1!N11>40000,Sheet1!K11="Laptop"),"Yes","No") -> No
A61: =Sheet1!J12 -> 2011 | B61: =Sheet1!K12 -> Keyboard | C61: =Sheet1!L12 -> East | D61: =Sheet1!M12 -> Person 11 | E61: =Sheet1!N12 -> 33920 | F61: =IF(OR(Sheet1!N12>40000,Sheet1!K12="Laptop"),"Yes","No") -> No
A62: =Sheet1!J13 -> 2012 | B62: =Sheet1!K13 -> Monitor | C62: =Sheet1!L13 -> North | D62: =Sheet1!M13 -> Person 12 | E62: =Sheet1!N13 -> 35611 | F62: =IF(OR(Sheet1!N13>40000,Sheet1!K13="Laptop"),"Yes","No") -> No
... A70: =Sheet1!J21 -> 2020 | B70: =Sheet1!K21 -> Printer | C70: =Sheet1!L21 -> West | D70: =Sheet1!M21 -> Person 20 | E70: =Sheet1!N21 -> 33953 | F70: =IF(OR(Sheet1!N21>40000,Sheet1!K21="Laptop"),"Yes","No") -> No
A72: 4. COUNTIFS / SUMIFS / AVERAGEIFS
A73: Task | B73: Formula Used | C73: Result | D73: Notes
A74: Students scoring > 50 in Math | B74: =COUNTIFS(Sheet1!E2:E21,">50") -> 19 | C74: =COUNTIFS(Sheet1!E2:E21,">50") -> 19 | D74: COUNTIFS with single criterion on Math column
A75: Students scoring > 60 in Math (avg score) | B75: =AVERAGEIFS(Sheet1!E2:E21,Sheet1!E2:E21,">60") -> 82.263158 | C75: =AVERAGEIFS(Sheet1!E2:E21,Sheet1!E2:E21,">60") -> 82.263158 | D75: AVERAGEIFS: average Math scores where Math > 60
A76: Total Sales – East region, Keyboard | B76: =SUMIFS(Sheet1!N2:N21,Sheet1!L2:L21,"East",Sheet1!K2:K21,"Keyboard") -> 80349 | C76: =SUMIFS(Sheet1!N2:N21,Sheet1!L2:L21,"East",Sheet1!K2:K21,"Keyboard") -> 80349 | D76: SUMIFS: sum amounts where Region=East AND Product=Keyboard
A78: 5. VLOOKUP – Fetch Student Name by ID & Fetch Product Amount by Sales ID
A79: Lookup Value | B79: Result
A80: 1005 | B80: =VLOOKUP(1005,Sheet1!$C$2:$G$21,2,0) -> Student 5
A81: 1013 | B81: =VLOOKUP(1013,Sheet1!$C$2:$G$21,2,0) -> Student 13
A82: 2007 | B82: =VLOOKUP(2007,Sheet1!$J$2:$N$21,5,0) -> 32058
A83: 2015 | B83: =VLOOKUP(2015,Sheet1!$J$2:$N$21,2,0) -> Laptop
A87: 6. XLOOKUP – Employee Salary & Salesperson Amount (flexible, no sort required)
A88: Lookup Value | B88: Result
A89: Employee 5 | B89: =INDEX(Sheet1!$T$2:$T$21,MATCH("Employee 5",Sheet1!$R$2:$R$21,0)) -> 54149
A90: Employee 12 | B90: =INDEX(Sheet1!$T$2:$T$21,MATCH("Employee 12",Sheet1!$R$2:$R$21,0)) -> 35226
A91: Person 8 | B91: =INDEX(Sheet1!$N$2:$N$21,MATCH("Person 8",Sheet1!$M$2:$M$21,0)) -> 46429
A92: Person 17 | B92: =INDEX(Sheet1!$N$2:$N$21,MATCH("Person 17",Sheet1!$M$2:$M$21,0)) -> 41871
A94: 7. XMATCH – Find Position of Product in Sales List
A95: Search Value | B95: Position
A96: Monitor | B96: =MATCH("Monitor",Sheet1!$K$2:$K$21,0) -> 12
A97: Laptop | B97: =MATCH("Laptop",Sheet1!$K$2:$K$21,0) -> 13
A98: Person 15 | B98: =MATCH("Person 15",Sheet1!$M$2:$M$21,0) -> 15
A100: 8. INDEX / MATCH – Dynamic Employee & Sales Lookups
A101: Lookup Value | B101: Result
A102: Employee 7 | B102: =INDEX(Sheet1!$T$2:$T$21,MATCH("Employee 7",Sheet1!$R$2:$R$21,0)) -> 35960
A103: Employee 14 | B103: =INDEX(Sheet1!$S$2:$S$21,MATCH("Employee 14",Sheet1!$R$2:$R$21,0)) -> HR
A104: 3009 | B104: =INDEX(Sheet1!$R$2:$R$21,MATCH(3009,Sheet1!$Q$2:$Q$21,0)) -> Employee 9
A105: Person 10 | B105: =INDEX(Sheet1!$K$2:$K$21,MATCH("Person 10",Sheet1!$M$2:$M$21,0)) -> Keyboard
A107: 9. TEXT Functions – LEFT/FIND, UPPER, LOWER, LEN, PROPER on Employee Names
A108: Employee Name | B108: First Word (LEFT/FIND) | C108: UPPER | D108: LOWER | E108: Length (LEN) | F108: PROPER
A109: =Sheet1!R2 -> Employee 1 | B109: =LEFT(Sheet1!R2,FIND(" ",Sheet1!R2)-1) -> Employee | C109: =UPPER(Sheet1!R2) -> EMPLOYEE 1 | D109: =LOWER(Sheet1!R2) -> employee 1 | E109: =LEN(Sheet1!R2) -> 10 | F109: =PROPER(Sheet1!R2) -> Employee 1
A110: =Sheet1!R3 -> Employee 2 | B110: =LEFT(Sheet1!R3,FIND(" ",Sheet1!R3)-1) -> Employee | C110: =UPPER(Sheet1!R3) -> EMPLOYEE 2 | D110: =LOWER(Sheet1!R3) -> employee 2 | E110: =LEN(Sheet1!R3) -> 10 | F110: =PROPER(Sheet1!R3) -> Employee 2
A111: =Sheet1!R4 -> Employee 3 | B111: =LEFT(Sheet1!R4,FIND(" ",Sheet1!R4)-1) -> Employee | C111: =UPPER(Sheet1!R4) -> EMPLOYEE 3 | D111: =LOWER(Sheet1!R4) -> employee 3 | E111: =LEN(Sheet1!R4) -> 10 | F111: =PROPER(Sheet1!R4) -> Employee 3
A112: =Sheet1!R5 -> Employee 4 | B112: =LEFT(Sheet1!R5,FIND(" ",Sheet1!R5)-1) -> Employee | C112: =UPPER(Sheet1!R5) -> EMPLOYEE 4 | D112: =LOWER(Sheet1!R5) -> employee 4 | E112: =LEN(Sheet1!R5) -> 10 | F112: =PROPER(Sheet1!R5) -> Employee 4
A113: =Sheet1!R6 -> Employee 5 | B113: =LEFT(Sheet1!R6,FIND(" ",Sheet1!R6)-1) -> Employee | C113: =UPPER(Sheet1!R6) -> EMPLOYEE 5 | D113: =LOWER(Sheet1!R6) -> employee 5 | E113: =LEN(Sheet1!R6) -> 10 | F113: =PROPER(Sheet1!R6) -> Employee 5
A114: =Sheet1!R7 -> Employee 6 | B114: =LEFT(Sheet1!R7,FIND(" ",Sheet1!R7)-1) -> Employee | C114: =UPPER(Sheet1!R7) -> EMPLOYEE 6 | D114: =LOWER(Sheet1!R7) -> employee 6 | E114: =LEN(Sheet1!R7) -> 10 | F114: =PROPER(Sheet1!R7) -> Employee 6
A115: =Sheet1!R8 -> Employee 7 | B115: =LEFT(Sheet1!R8,FIND(" ",Sheet1!R8)-1) -> Employee | C115: =UPPER(Sheet1!R8) -> EMPLOYEE 7 | D115: =LOWER(Sheet1!R8) -> employee 7 | E115: =LEN(Sheet1!R8) -> 10 | F115: =PROPER(Sheet1!R8) -> Employee 7
A116: =Sheet1!R9 -> Employee 8 | B116: =LEFT(Sheet1!R9,FIND(" ",Sheet1!R9)-1) -> Employee | C116: =UPPER(Sheet1!R9) -> EMPLOYEE 8 | D116: =LOWER(Sheet1!R9) -> employee 8 | E116: =LEN(Sheet1!R9) -> 10 | F116: =PROPER(Sheet1!R9) -> Employee 8
A117: =Sheet1!R10 -> Employee 9 | B117: =LEFT(Sheet1!R10,FIND(" ",Sheet1!R10)-1) -> Employee | C117: =UPPER(Sheet1!R10) -> EMPLOYEE 9 | D117: =LOWER(Sheet1!R10) -> employee 9 | E117: =LEN(Sheet1!R10) -> 10 | F117: =PROPER(Sheet1!R10) -> Employee 9
A118: =Sheet1!R11 -> Employee 10 | B118: =LEFT(Sheet1!R11,FIND(" ",Sheet1!R11)-1) -> Employee | C118: =UPPER(Sheet1!R11) -> EMPLOYEE 10 | D118: =LOWER(Sheet1!R11) -> employee 10 | E118: =LEN(Sheet1!R11) -> 11 | F118: =PROPER(Sheet1!R11) -> Employee 10
A120: 10. INDIRECT – Dynamically Reference Cell Ranges
A121: Cell Reference (text) | B121: Result
A122: Sheet1!E2 | B122: =INDIRECT("Sheet1!E2") -> 61
A123: Sheet1!N5 | B123: =INDIRECT("Sheet1!N5") -> 5264
A124: Sheet1!T10 | B124: =INDIRECT("Sheet1!T10") -> 90423
A125: SUM range | B125: =SUM(INDIRECT("Sheet1!E2:E21")) -> 1604
A126: AVG range | B126: =AVERAGE(INDIRECT("Sheet1!N2:N21")) -> 25386.25
A128: 11. OFFSET – Dynamic Ranges for Sales Trends
A129: Task | B129: Result
A130: Value 3 rows below N2 | B130: =OFFSET(Sheet1!N2,3,0) -> 5264
A131: Sum first 5 sales | B131: =SUM(OFFSET(Sheet1!N2,0,0,5,1)) -> 96800
A132: Sum last 5 sales | B132: =SUM(OFFSET(Sheet1!N21,-4,0,5,1)) -> 149698
A133: Avg first 10 Math scores | B133: =AVERAGE(OFFSET(Sheet1!E2,0,0,10,1)) -> 76.6
A135: 12. Date & Time Functions – Age, Years of Service, Days Between Dates
...
